area51/__init__.py
area51/area51.py
ashish-0.1.0.dist-info/METADATA
ashish-0.1.0.dist-info/WHEEL
ashish-0.1.0.dist-info/top_level.txt
ashish-0.1.0.dist-info/RECORD
