Metadata-Version: 2.1
Name: ashish
Version: 0.1.0
Summary: A very basic area calculater library
Author: Ashish
Author-email: ashish@email.com
Requires-Python: >=3.6
